setup.py
digCrfTokenizer/__init__.py
digCrfTokenizer/crf_tokenizer.py
digCrfTokenizer.egg-info/PKG-INFO
digCrfTokenizer.egg-info/SOURCES.txt
digCrfTokenizer.egg-info/dependency_links.txt
digCrfTokenizer.egg-info/top_level.txt