Metadata-Version: 1.1
Name: digCrfTokenizer
Version: 0.1.6
Summary: digCrfTokenizer
Home-page: https://github.com/usc-isi-i2/dig-crf-tokenizer
Author: Craig Milo Rogers
Author-email: rogers@isi.edu
License: Apache License 2.0
Download-URL: https://github.com/usc-isi-i2/dig-crf-tokenizer
Platform: UNKNOWN
